MANIFEST.in
README.md
README.rst
setup.cfg
setup.py
bin/dotplot
dotplot/__init__.py
dotplot/__main__.py
dotplot/argument_parser.py
dotplot/dotplot.py
dotplot/drawer.py
dotplot/figures_plot.py
dotplot/helpers.py
dotplot/main.py
dotplot/matrices.py
dotplot/plotter.py
dotplot/sequence.py
dotplot.egg-info/PKG-INFO
dotplot.egg-info/SOURCES.txt
dotplot.egg-info/dependency_links.txt
dotplot.egg-info/requires.txt
dotplot.egg-info/top_level.txt
dotplot/gui/__init__.py
dotplot/gui/chooser.py
dotplot/gui/helpers.py
dotplot/gui/main_window.py
dotplot/gui/options.py
dotplot/matrices/PAM120.txt